{
  "generated_at": "2026-05-31T13:04:31.188557-04:00",
  "scopes": {
    "daily": {
      "overall": {
        "record": "0-0-0",
        "wins": 0,
        "losses": 0,
        "pushes": 0,
        "pending": 6,
        "total_picks": 6,
        "settled_picks": 0,
        "units_pl": 0,
        "roi_pct": 0.0,
        "win_rate_pct": 0.0,
        "avg_clv_cents": 0.0,
        "longest_w_streak": 0,
        "longest_l_streak": 0,
        "biggest_win_units": 0,
        "biggest_loss_units": 0
      },
      "by_sport": {
        "MLB": {
          "record": "0-0-0",
          "wins": 0,
          "losses": 0,
          "pushes": 0,
          "pending": 6,
          "total_picks": 6,
          "settled_picks": 0,
          "units_pl": 0,
          "roi_pct": 0.0,
          "win_rate_pct": 0.0,
          "avg_clv_cents": 0.0,
          "longest_w_streak": 0,
          "longest_l_streak": 0,
          "biggest_win_units": 0,
          "biggest_loss_units": 0
        }
      },
      "by_confidence": {
        "3": {
          "record": "0-0-0",
          "wins": 0,
          "losses": 0,
          "pushes": 0,
          "pending": 2,
          "total_picks": 2,
          "settled_picks": 0,
          "units_pl": 0,
          "roi_pct": 0.0,
          "win_rate_pct": 0.0,
          "avg_clv_cents": 0.0,
          "longest_w_streak": 0,
          "longest_l_streak": 0,
          "biggest_win_units": 0,
          "biggest_loss_units": 0
        },
        "4": {
          "record": "0-0-0",
          "wins": 0,
          "losses": 0,
          "pushes": 0,
          "pending": 3,
          "total_picks": 3,
          "settled_picks": 0,
          "units_pl": 0,
          "roi_pct": 0.0,
          "win_rate_pct": 0.0,
          "avg_clv_cents": 0.0,
          "longest_w_streak": 0,
          "longest_l_streak": 0,
          "biggest_win_units": 0,
          "biggest_loss_units": 0
        },
        "5": {
          "record": "0-0-0",
          "wins": 0,
          "losses": 0,
          "pushes": 0,
          "pending": 1,
          "total_picks": 1,
          "settled_picks": 0,
          "units_pl": 0,
          "roi_pct": 0.0,
          "win_rate_pct": 0.0,
          "avg_clv_cents": 0.0,
          "longest_w_streak": 0,
          "longest_l_streak": 0,
          "biggest_win_units": 0,
          "biggest_loss_units": 0
        }
      },
      "by_pick_type": {
        "ML": {
          "record": "0-0-0",
          "wins": 0,
          "losses": 0,
          "pushes": 0,
          "pending": 1,
          "total_picks": 1,
          "settled_picks": 0,
          "units_pl": 0,
          "roi_pct": 0.0,
          "win_rate_pct": 0.0,
          "avg_clv_cents": 0.0,
          "longest_w_streak": 0,
          "longest_l_streak": 0,
          "biggest_win_units": 0,
          "biggest_loss_units": 0
        },
        "PROP": {
          "record": "0-0-0",
          "wins": 0,
          "losses": 0,
          "pushes": 0,
          "pending": 1,
          "total_picks": 1,
          "settled_picks": 0,
          "units_pl": 0,
          "roi_pct": 0.0,
          "win_rate_pct": 0.0,
          "avg_clv_cents": 0.0,
          "longest_w_streak": 0,
          "longest_l_streak": 0,
          "biggest_win_units": 0,
          "biggest_loss_units": 0
        },
        "SPREAD": {
          "record": "0-0-0",
          "wins": 0,
          "losses": 0,
          "pushes": 0,
          "pending": 1,
          "total_picks": 1,
          "settled_picks": 0,
          "units_pl": 0,
          "roi_pct": 0.0,
          "win_rate_pct": 0.0,
          "avg_clv_cents": 0.0,
          "longest_w_streak": 0,
          "longest_l_streak": 0,
          "biggest_win_units": 0,
          "biggest_loss_units": 0
        },
        "TOTAL": {
          "record": "0-0-0",
          "wins": 0,
          "losses": 0,
          "pushes": 0,
          "pending": 3,
          "total_picks": 3,
          "settled_picks": 0,
          "units_pl": 0,
          "roi_pct": 0.0,
          "win_rate_pct": 0.0,
          "avg_clv_cents": 0.0,
          "longest_w_streak": 0,
          "longest_l_streak": 0,
          "biggest_win_units": 0,
          "biggest_loss_units": 0
        }
      }
    },
    "weekly": {
      "overall": {
        "record": "19-12-0",
        "wins": 19,
        "losses": 12,
        "pushes": 0,
        "pending": 6,
        "total_picks": 37,
        "settled_picks": 31,
        "units_pl": 8.767,
        "roi_pct": 20.63,
        "win_rate_pct": 61.29,
        "avg_clv_cents": 0.0,
        "longest_w_streak": 4,
        "longest_l_streak": 3,
        "biggest_win_units": 2.2,
        "biggest_loss_units": -1.5
      },
      "by_sport": {
        "MLB": {
          "record": "15-9-0",
          "wins": 15,
          "losses": 9,
          "pushes": 0,
          "pending": 6,
          "total_picks": 30,
          "settled_picks": 24,
          "units_pl": 6.473,
          "roi_pct": 19.62,
          "win_rate_pct": 62.5,
          "avg_clv_cents": 0.0,
          "longest_w_streak": 5,
          "longest_l_streak": 3,
          "biggest_win_units": 1.818,
          "biggest_loss_units": -1.5
        },
        "NBA": {
          "record": "3-2-0",
          "wins": 3,
          "losses": 2,
          "pushes": 0,
          "pending": 0,
          "total_picks": 5,
          "settled_picks": 5,
          "units_pl": 1.093,
          "roi_pct": 16.82,
          "win_rate_pct": 60.0,
          "avg_clv_cents": 0.0,
          "longest_w_streak": 2,
          "longest_l_streak": 2,
          "biggest_win_units": 1.389,
          "biggest_loss_units": -1.5
        },
        "NHL": {
          "record": "1-1-0",
          "wins": 1,
          "losses": 1,
          "pushes": 0,
          "pending": 0,
          "total_picks": 2,
          "settled_picks": 2,
          "units_pl": 1.2,
          "roi_pct": 40.0,
          "win_rate_pct": 50.0,
          "avg_clv_cents": 0.0,
          "longest_w_streak": 1,
          "longest_l_streak": 1,
          "biggest_win_units": 2.2,
          "biggest_loss_units": -1.0
        }
      },
      "by_confidence": {
        "3": {
          "record": "7-4-0",
          "wins": 7,
          "losses": 4,
          "pushes": 0,
          "pending": 2,
          "total_picks": 13,
          "settled_picks": 11,
          "units_pl": 2.365,
          "roi_pct": 21.5,
          "win_rate_pct": 63.64,
          "avg_clv_cents": 0.0,
          "longest_w_streak": 3,
          "longest_l_streak": 2,
          "biggest_win_units": 1.0,
          "biggest_loss_units": -1.0
        },
        "4": {
          "record": "9-8-0",
          "wins": 9,
          "losses": 8,
          "pushes": 0,
          "pending": 3,
          "total_picks": 20,
          "settled_picks": 17,
          "units_pl": 0.689,
          "roi_pct": 2.7,
          "win_rate_pct": 52.94,
          "avg_clv_cents": 0.0,
          "longest_w_streak": 3,
          "longest_l_streak": 3,
          "biggest_win_units": 1.8,
          "biggest_loss_units": -1.5
        },
        "5": {
          "record": "3-0-0",
          "wins": 3,
          "losses": 0,
          "pushes": 0,
          "pending": 1,
          "total_picks": 4,
          "settled_picks": 3,
          "units_pl": 5.713,
          "roi_pct": 95.22,
          "win_rate_pct": 100.0,
          "avg_clv_cents": 0.0,
          "longest_w_streak": 3,
          "longest_l_streak": 0,
          "biggest_win_units": 2.2,
          "biggest_loss_units": 0
        }
      },
      "by_pick_type": {
        "ML": {
          "record": "2-3-0",
          "wins": 2,
          "losses": 3,
          "pushes": 0,
          "pending": 1,
          "total_picks": 6,
          "settled_picks": 5,
          "units_pl": -2.041,
          "roi_pct": -31.41,
          "win_rate_pct": 40.0,
          "avg_clv_cents": 0.0,
          "longest_w_streak": 2,
          "longest_l_streak": 3,
          "biggest_win_units": 1.111,
          "biggest_loss_units": -1.5
        },
        "PROP": {
          "record": "4-2-0",
          "wins": 4,
          "losses": 2,
          "pushes": 0,
          "pending": 1,
          "total_picks": 7,
          "settled_picks": 6,
          "units_pl": 1.566,
          "roi_pct": 22.37,
          "win_rate_pct": 66.67,
          "avg_clv_cents": 0.0,
          "longest_w_streak": 2,
          "longest_l_streak": 1,
          "biggest_win_units": 1.327,
          "biggest_loss_units": -1.5
        },
        "RUNLINE": {
          "record": "3-0-0",
          "wins": 3,
          "losses": 0,
          "pushes": 0,
          "pending": 0,
          "total_picks": 3,
          "settled_picks": 3,
          "units_pl": 4.404,
          "roi_pct": 97.87,
          "win_rate_pct": 100.0,
          "avg_clv_cents": 0.0,
          "longest_w_streak": 3,
          "longest_l_streak": 0,
          "biggest_win_units": 1.8,
          "biggest_loss_units": 0
        },
        "SPREAD": {
          "record": "3-1-0",
          "wins": 3,
          "losses": 1,
          "pushes": 0,
          "pending": 1,
          "total_picks": 5,
          "settled_picks": 4,
          "units_pl": 3.589,
          "roi_pct": 55.21,
          "win_rate_pct": 75.0,
          "avg_clv_cents": 0.0,
          "longest_w_streak": 3,
          "longest_l_streak": 1,
          "biggest_win_units": 2.2,
          "biggest_loss_units": -1.5
        },
        "TOTAL": {
          "record": "7-6-0",
          "wins": 7,
          "losses": 6,
          "pushes": 0,
          "pending": 3,
          "total_picks": 16,
          "settled_picks": 13,
          "units_pl": 1.249,
          "roi_pct": 6.94,
          "win_rate_pct": 53.85,
          "avg_clv_cents": 0.0,
          "longest_w_streak": 3,
          "longest_l_streak": 3,
          "biggest_win_units": 1.818,
          "biggest_loss_units": -1.5
        }
      }
    },
    "monthly": {
      "overall": {
        "record": "27-18-0",
        "wins": 27,
        "losses": 18,
        "pushes": 0,
        "pending": 6,
        "total_picks": 51,
        "settled_picks": 45,
        "units_pl": 10.508,
        "roi_pct": 17.51,
        "win_rate_pct": 60.0,
        "avg_clv_cents": 0.0,
        "longest_w_streak": 4,
        "longest_l_streak": 3,
        "biggest_win_units": 2.2,
        "biggest_loss_units": -1.5
      },
      "by_sport": {
        "MLB": {
          "record": "23-14-0",
          "wins": 23,
          "losses": 14,
          "pushes": 0,
          "pending": 6,
          "total_picks": 43,
          "settled_picks": 37,
          "units_pl": 9.215,
          "roi_pct": 18.62,
          "win_rate_pct": 62.16,
          "avg_clv_cents": 0.0,
          "longest_w_streak": 5,
          "longest_l_streak": 3,
          "biggest_win_units": 1.818,
          "biggest_loss_units": -1.5
        },
        "NBA": {
          "record": "3-3-0",
          "wins": 3,
          "losses": 3,
          "pushes": 0,
          "pending": 0,
          "total_picks": 6,
          "settled_picks": 6,
          "units_pl": 0.093,
          "roi_pct": 1.25,
          "win_rate_pct": 50.0,
          "avg_clv_cents": 0.0,
          "longest_w_streak": 2,
          "longest_l_streak": 2,
          "biggest_win_units": 1.389,
          "biggest_loss_units": -1.5
        },
        "NHL": {
          "record": "1-1-0",
          "wins": 1,
          "losses": 1,
          "pushes": 0,
          "pending": 0,
          "total_picks": 2,
          "settled_picks": 2,
          "units_pl": 1.2,
          "roi_pct": 40.0,
          "win_rate_pct": 50.0,
          "avg_clv_cents": 0.0,
          "longest_w_streak": 1,
          "longest_l_streak": 1,
          "biggest_win_units": 2.2,
          "biggest_loss_units": -1.0
        }
      },
      "by_confidence": {
        "3": {
          "record": "11-7-0",
          "wins": 11,
          "losses": 7,
          "pushes": 0,
          "pending": 2,
          "total_picks": 20,
          "settled_picks": 18,
          "units_pl": 3.362,
          "roi_pct": 18.68,
          "win_rate_pct": 61.11,
          "avg_clv_cents": 0.0,
          "longest_w_streak": 5,
          "longest_l_streak": 2,
          "biggest_win_units": 1.25,
          "biggest_loss_units": -1.0
        },
        "4": {
          "record": "13-11-0",
          "wins": 13,
          "losses": 11,
          "pushes": 0,
          "pending": 3,
          "total_picks": 27,
          "settled_picks": 24,
          "units_pl": 1.433,
          "roi_pct": 3.98,
          "win_rate_pct": 54.17,
          "avg_clv_cents": 0.0,
          "longest_w_streak": 3,
          "longest_l_streak": 3,
          "biggest_win_units": 1.8,
          "biggest_loss_units": -1.5
        },
        "5": {
          "record": "3-0-0",
          "wins": 3,
          "losses": 0,
          "pushes": 0,
          "pending": 1,
          "total_picks": 4,
          "settled_picks": 3,
          "units_pl": 5.713,
          "roi_pct": 95.22,
          "win_rate_pct": 100.0,
          "avg_clv_cents": 0.0,
          "longest_w_streak": 3,
          "longest_l_streak": 0,
          "biggest_win_units": 2.2,
          "biggest_loss_units": 0
        }
      },
      "by_pick_type": {
        "ML": {
          "record": "4-4-0",
          "wins": 4,
          "losses": 4,
          "pushes": 0,
          "pending": 1,
          "total_picks": 9,
          "settled_picks": 8,
          "units_pl": -1.458,
          "roi_pct": -14.58,
          "win_rate_pct": 50.0,
          "avg_clv_cents": 0.0,
          "longest_w_streak": 2,
          "longest_l_streak": 4,
          "biggest_win_units": 1.25,
          "biggest_loss_units": -1.5
        },
        "PROP": {
          "record": "4-2-0",
          "wins": 4,
          "losses": 2,
          "pushes": 0,
          "pending": 1,
          "total_picks": 7,
          "settled_picks": 6,
          "units_pl": 1.566,
          "roi_pct": 22.37,
          "win_rate_pct": 66.67,
          "avg_clv_cents": 0.0,
          "longest_w_streak": 2,
          "longest_l_streak": 1,
          "biggest_win_units": 1.327,
          "biggest_loss_units": -1.5
        },
        "RUNLINE": {
          "record": "3-0-0",
          "wins": 3,
          "losses": 0,
          "pushes": 0,
          "pending": 0,
          "total_picks": 3,
          "settled_picks": 3,
          "units_pl": 4.404,
          "roi_pct": 97.87,
          "win_rate_pct": 100.0,
          "avg_clv_cents": 0.0,
          "longest_w_streak": 3,
          "longest_l_streak": 0,
          "biggest_win_units": 1.8,
          "biggest_loss_units": 0
        },
        "SPREAD": {
          "record": "3-2-0",
          "wins": 3,
          "losses": 2,
          "pushes": 0,
          "pending": 1,
          "total_picks": 6,
          "settled_picks": 5,
          "units_pl": 2.589,
          "roi_pct": 34.52,
          "win_rate_pct": 60.0,
          "avg_clv_cents": 0.0,
          "longest_w_streak": 3,
          "longest_l_streak": 2,
          "biggest_win_units": 2.2,
          "biggest_loss_units": -1.5
        },
        "TOTAL": {
          "record": "13-10-0",
          "wins": 13,
          "losses": 10,
          "pushes": 0,
          "pending": 3,
          "total_picks": 26,
          "settled_picks": 23,
          "units_pl": 3.407,
          "roi_pct": 10.99,
          "win_rate_pct": 56.52,
          "avg_clv_cents": 0.0,
          "longest_w_streak": 3,
          "longest_l_streak": 3,
          "biggest_win_units": 1.818,
          "biggest_loss_units": -1.5
        }
      }
    },
    "yearly": {
      "overall": {
        "record": "27-18-0",
        "wins": 27,
        "losses": 18,
        "pushes": 0,
        "pending": 6,
        "total_picks": 51,
        "settled_picks": 45,
        "units_pl": 10.508,
        "roi_pct": 17.51,
        "win_rate_pct": 60.0,
        "avg_clv_cents": 0.0,
        "longest_w_streak": 4,
        "longest_l_streak": 3,
        "biggest_win_units": 2.2,
        "biggest_loss_units": -1.5
      },
      "by_sport": {
        "MLB": {
          "record": "23-14-0",
          "wins": 23,
          "losses": 14,
          "pushes": 0,
          "pending": 6,
          "total_picks": 43,
          "settled_picks": 37,
          "units_pl": 9.215,
          "roi_pct": 18.62,
          "win_rate_pct": 62.16,
          "avg_clv_cents": 0.0,
          "longest_w_streak": 5,
          "longest_l_streak": 3,
          "biggest_win_units": 1.818,
          "biggest_loss_units": -1.5
        },
        "NBA": {
          "record": "3-3-0",
          "wins": 3,
          "losses": 3,
          "pushes": 0,
          "pending": 0,
          "total_picks": 6,
          "settled_picks": 6,
          "units_pl": 0.093,
          "roi_pct": 1.25,
          "win_rate_pct": 50.0,
          "avg_clv_cents": 0.0,
          "longest_w_streak": 2,
          "longest_l_streak": 2,
          "biggest_win_units": 1.389,
          "biggest_loss_units": -1.5
        },
        "NHL": {
          "record": "1-1-0",
          "wins": 1,
          "losses": 1,
          "pushes": 0,
          "pending": 0,
          "total_picks": 2,
          "settled_picks": 2,
          "units_pl": 1.2,
          "roi_pct": 40.0,
          "win_rate_pct": 50.0,
          "avg_clv_cents": 0.0,
          "longest_w_streak": 1,
          "longest_l_streak": 1,
          "biggest_win_units": 2.2,
          "biggest_loss_units": -1.0
        }
      },
      "by_confidence": {
        "3": {
          "record": "11-7-0",
          "wins": 11,
          "losses": 7,
          "pushes": 0,
          "pending": 2,
          "total_picks": 20,
          "settled_picks": 18,
          "units_pl": 3.362,
          "roi_pct": 18.68,
          "win_rate_pct": 61.11,
          "avg_clv_cents": 0.0,
          "longest_w_streak": 5,
          "longest_l_streak": 2,
          "biggest_win_units": 1.25,
          "biggest_loss_units": -1.0
        },
        "4": {
          "record": "13-11-0",
          "wins": 13,
          "losses": 11,
          "pushes": 0,
          "pending": 3,
          "total_picks": 27,
          "settled_picks": 24,
          "units_pl": 1.433,
          "roi_pct": 3.98,
          "win_rate_pct": 54.17,
          "avg_clv_cents": 0.0,
          "longest_w_streak": 3,
          "longest_l_streak": 3,
          "biggest_win_units": 1.8,
          "biggest_loss_units": -1.5
        },
        "5": {
          "record": "3-0-0",
          "wins": 3,
          "losses": 0,
          "pushes": 0,
          "pending": 1,
          "total_picks": 4,
          "settled_picks": 3,
          "units_pl": 5.713,
          "roi_pct": 95.22,
          "win_rate_pct": 100.0,
          "avg_clv_cents": 0.0,
          "longest_w_streak": 3,
          "longest_l_streak": 0,
          "biggest_win_units": 2.2,
          "biggest_loss_units": 0
        }
      },
      "by_pick_type": {
        "ML": {
          "record": "4-4-0",
          "wins": 4,
          "losses": 4,
          "pushes": 0,
          "pending": 1,
          "total_picks": 9,
          "settled_picks": 8,
          "units_pl": -1.458,
          "roi_pct": -14.58,
          "win_rate_pct": 50.0,
          "avg_clv_cents": 0.0,
          "longest_w_streak": 2,
          "longest_l_streak": 4,
          "biggest_win_units": 1.25,
          "biggest_loss_units": -1.5
        },
        "PROP": {
          "record": "4-2-0",
          "wins": 4,
          "losses": 2,
          "pushes": 0,
          "pending": 1,
          "total_picks": 7,
          "settled_picks": 6,
          "units_pl": 1.566,
          "roi_pct": 22.37,
          "win_rate_pct": 66.67,
          "avg_clv_cents": 0.0,
          "longest_w_streak": 2,
          "longest_l_streak": 1,
          "biggest_win_units": 1.327,
          "biggest_loss_units": -1.5
        },
        "RUNLINE": {
          "record": "3-0-0",
          "wins": 3,
          "losses": 0,
          "pushes": 0,
          "pending": 0,
          "total_picks": 3,
          "settled_picks": 3,
          "units_pl": 4.404,
          "roi_pct": 97.87,
          "win_rate_pct": 100.0,
          "avg_clv_cents": 0.0,
          "longest_w_streak": 3,
          "longest_l_streak": 0,
          "biggest_win_units": 1.8,
          "biggest_loss_units": 0
        },
        "SPREAD": {
          "record": "3-2-0",
          "wins": 3,
          "losses": 2,
          "pushes": 0,
          "pending": 1,
          "total_picks": 6,
          "settled_picks": 5,
          "units_pl": 2.589,
          "roi_pct": 34.52,
          "win_rate_pct": 60.0,
          "avg_clv_cents": 0.0,
          "longest_w_streak": 3,
          "longest_l_streak": 2,
          "biggest_win_units": 2.2,
          "biggest_loss_units": -1.5
        },
        "TOTAL": {
          "record": "13-10-0",
          "wins": 13,
          "losses": 10,
          "pushes": 0,
          "pending": 3,
          "total_picks": 26,
          "settled_picks": 23,
          "units_pl": 3.407,
          "roi_pct": 10.99,
          "win_rate_pct": 56.52,
          "avg_clv_cents": 0.0,
          "longest_w_streak": 3,
          "longest_l_streak": 3,
          "biggest_win_units": 1.818,
          "biggest_loss_units": -1.5
        }
      }
    },
    "all_time": {
      "overall": {
        "record": "27-18-0",
        "wins": 27,
        "losses": 18,
        "pushes": 0,
        "pending": 6,
        "total_picks": 51,
        "settled_picks": 45,
        "units_pl": 10.508,
        "roi_pct": 17.51,
        "win_rate_pct": 60.0,
        "avg_clv_cents": 0.0,
        "longest_w_streak": 4,
        "longest_l_streak": 3,
        "biggest_win_units": 2.2,
        "biggest_loss_units": -1.5
      },
      "by_sport": {
        "MLB": {
          "record": "23-14-0",
          "wins": 23,
          "losses": 14,
          "pushes": 0,
          "pending": 6,
          "total_picks": 43,
          "settled_picks": 37,
          "units_pl": 9.215,
          "roi_pct": 18.62,
          "win_rate_pct": 62.16,
          "avg_clv_cents": 0.0,
          "longest_w_streak": 5,
          "longest_l_streak": 3,
          "biggest_win_units": 1.818,
          "biggest_loss_units": -1.5
        },
        "NBA": {
          "record": "3-3-0",
          "wins": 3,
          "losses": 3,
          "pushes": 0,
          "pending": 0,
          "total_picks": 6,
          "settled_picks": 6,
          "units_pl": 0.093,
          "roi_pct": 1.25,
          "win_rate_pct": 50.0,
          "avg_clv_cents": 0.0,
          "longest_w_streak": 2,
          "longest_l_streak": 2,
          "biggest_win_units": 1.389,
          "biggest_loss_units": -1.5
        },
        "NHL": {
          "record": "1-1-0",
          "wins": 1,
          "losses": 1,
          "pushes": 0,
          "pending": 0,
          "total_picks": 2,
          "settled_picks": 2,
          "units_pl": 1.2,
          "roi_pct": 40.0,
          "win_rate_pct": 50.0,
          "avg_clv_cents": 0.0,
          "longest_w_streak": 1,
          "longest_l_streak": 1,
          "biggest_win_units": 2.2,
          "biggest_loss_units": -1.0
        }
      },
      "by_confidence": {
        "3": {
          "record": "11-7-0",
          "wins": 11,
          "losses": 7,
          "pushes": 0,
          "pending": 2,
          "total_picks": 20,
          "settled_picks": 18,
          "units_pl": 3.362,
          "roi_pct": 18.68,
          "win_rate_pct": 61.11,
          "avg_clv_cents": 0.0,
          "longest_w_streak": 5,
          "longest_l_streak": 2,
          "biggest_win_units": 1.25,
          "biggest_loss_units": -1.0
        },
        "4": {
          "record": "13-11-0",
          "wins": 13,
          "losses": 11,
          "pushes": 0,
          "pending": 3,
          "total_picks": 27,
          "settled_picks": 24,
          "units_pl": 1.433,
          "roi_pct": 3.98,
          "win_rate_pct": 54.17,
          "avg_clv_cents": 0.0,
          "longest_w_streak": 3,
          "longest_l_streak": 3,
          "biggest_win_units": 1.8,
          "biggest_loss_units": -1.5
        },
        "5": {
          "record": "3-0-0",
          "wins": 3,
          "losses": 0,
          "pushes": 0,
          "pending": 1,
          "total_picks": 4,
          "settled_picks": 3,
          "units_pl": 5.713,
          "roi_pct": 95.22,
          "win_rate_pct": 100.0,
          "avg_clv_cents": 0.0,
          "longest_w_streak": 3,
          "longest_l_streak": 0,
          "biggest_win_units": 2.2,
          "biggest_loss_units": 0
        }
      },
      "by_pick_type": {
        "ML": {
          "record": "4-4-0",
          "wins": 4,
          "losses": 4,
          "pushes": 0,
          "pending": 1,
          "total_picks": 9,
          "settled_picks": 8,
          "units_pl": -1.458,
          "roi_pct": -14.58,
          "win_rate_pct": 50.0,
          "avg_clv_cents": 0.0,
          "longest_w_streak": 2,
          "longest_l_streak": 4,
          "biggest_win_units": 1.25,
          "biggest_loss_units": -1.5
        },
        "PROP": {
          "record": "4-2-0",
          "wins": 4,
          "losses": 2,
          "pushes": 0,
          "pending": 1,
          "total_picks": 7,
          "settled_picks": 6,
          "units_pl": 1.566,
          "roi_pct": 22.37,
          "win_rate_pct": 66.67,
          "avg_clv_cents": 0.0,
          "longest_w_streak": 2,
          "longest_l_streak": 1,
          "biggest_win_units": 1.327,
          "biggest_loss_units": -1.5
        },
        "RUNLINE": {
          "record": "3-0-0",
          "wins": 3,
          "losses": 0,
          "pushes": 0,
          "pending": 0,
          "total_picks": 3,
          "settled_picks": 3,
          "units_pl": 4.404,
          "roi_pct": 97.87,
          "win_rate_pct": 100.0,
          "avg_clv_cents": 0.0,
          "longest_w_streak": 3,
          "longest_l_streak": 0,
          "biggest_win_units": 1.8,
          "biggest_loss_units": 0
        },
        "SPREAD": {
          "record": "3-2-0",
          "wins": 3,
          "losses": 2,
          "pushes": 0,
          "pending": 1,
          "total_picks": 6,
          "settled_picks": 5,
          "units_pl": 2.589,
          "roi_pct": 34.52,
          "win_rate_pct": 60.0,
          "avg_clv_cents": 0.0,
          "longest_w_streak": 3,
          "longest_l_streak": 2,
          "biggest_win_units": 2.2,
          "biggest_loss_units": -1.5
        },
        "TOTAL": {
          "record": "13-10-0",
          "wins": 13,
          "losses": 10,
          "pushes": 0,
          "pending": 3,
          "total_picks": 26,
          "settled_picks": 23,
          "units_pl": 3.407,
          "roi_pct": 10.99,
          "win_rate_pct": 56.52,
          "avg_clv_cents": 0.0,
          "longest_w_streak": 3,
          "longest_l_streak": 3,
          "biggest_win_units": 1.818,
          "biggest_loss_units": -1.5
        }
      }
    }
  },
  "current_streak": {
    "type": "WIN",
    "count": 1,
    "label": "W1 \u2191"
  },
  "clv_trend": [],
  "recent_form": [
    {
      "date": "2026-05-30",
      "pick": "Shai Gilgeous-Alexander Points Over 30.5",
      "result": "WIN",
      "units": 0.8772,
      "sport": "NBA",
      "ladder": false
    },
    {
      "date": "2026-05-30",
      "pick": "Victor Wembanyama Rebounds Over 12.5",
      "result": "LOSS",
      "units": -1.5,
      "sport": "NBA",
      "ladder": false
    },
    {
      "date": "2026-05-29",
      "pick": "Luis Arraez Hits Over 1.5",
      "result": "WIN",
      "units": 0.9091,
      "sport": "MLB",
      "ladder": false
    },
    {
      "date": "2026-05-29",
      "pick": "Matt Olson TBs Over 1.5",
      "result": "WIN",
      "units": 0.9524,
      "sport": "MLB",
      "ladder": false
    },
    {
      "date": "2026-05-28",
      "pick": "Shai Gilgeous-Alexander Points Over 29.5",
      "result": "LOSS",
      "units": -1.0,
      "sport": "NBA",
      "ladder": false
    },
    {
      "date": "2026-05-28",
      "pick": "Victor Wembanyama Points Over 27.5",
      "result": "WIN",
      "units": 1.3274,
      "sport": "NBA",
      "ladder": false
    },
    {
      "date": "2026-05-29",
      "pick": "Under 7.0",
      "result": "WIN",
      "units": 1.4851,
      "sport": "MLB",
      "ladder": false
    },
    {
      "date": "2026-05-29",
      "pick": "Under 8.0",
      "result": "WIN",
      "units": 1.4563,
      "sport": "MLB",
      "ladder": false
    },
    {
      "date": "2026-05-30",
      "pick": "Under 7",
      "result": "WIN",
      "units": 1.3043,
      "sport": "MLB",
      "ladder": false
    },
    {
      "date": "2026-05-30",
      "pick": "Under 6.5",
      "result": "LOSS",
      "units": -1.5,
      "sport": "MLB",
      "ladder": true
    },
    {
      "date": "2026-05-29",
      "pick": "Carolina Hurricanes -1.5",
      "result": "WIN",
      "units": 2.2,
      "sport": "NHL",
      "ladder": true
    },
    {
      "date": "2026-05-29",
      "pick": "Under 7.5",
      "result": "LOSS",
      "units": -1.5,
      "sport": "MLB",
      "ladder": false
    },
    {
      "date": "2026-05-28",
      "pick": "Atlanta Braves ML",
      "result": "WIN",
      "units": 1.1111,
      "sport": "MLB",
      "ladder": false
    },
    {
      "date": "2026-05-28",
      "pick": "San Antonio Spurs -3.5",
      "result": "WIN",
      "units": 1.3889,
      "sport": "NBA",
      "ladder": true
    },
    {
      "date": "2026-05-28",
      "pick": "Under 7.5",
      "result": "LOSS",
      "units": -1.0,
      "sport": "MLB",
      "ladder": false
    },
    {
      "date": "2026-05-27",
      "pick": "Under 9.0",
      "result": "WIN",
      "units": 1.8182,
      "sport": "MLB",
      "ladder": true
    },
    {
      "date": "2026-05-27",
      "pick": "Under 8.0",
      "result": "WIN",
      "units": 1.3158,
      "sport": "MLB",
      "ladder": false
    },
    {
      "date": "2026-05-27",
      "pick": "Under 7.0",
      "result": "LOSS",
      "units": -1.5,
      "sport": "MLB",
      "ladder": false
    },
    {
      "date": "2026-05-27",
      "pick": "Mets ML",
      "result": "WIN",
      "units": 0.8475,
      "sport": "MLB",
      "ladder": false
    },
    {
      "date": "2026-05-27",
      "pick": "Under 8.5",
      "result": "WIN",
      "units": 1.0,
      "sport": "MLB",
      "ladder": false
    }
  ],
  "ladder": {
    "state": {
      "current_streak": 0,
      "longest_streak": 4,
      "completed_climbs": 0,
      "target": 10,
      "history": [
        {
          "date": "2026-05-30",
          "pick_id": "20260530-MLB-BOS-CLE-TOTAL",
          "pick": "Under 6.5",
          "game": "BOS @ CLE",
          "status": "LOSS",
          "after_streak": 0
        },
        {
          "date": "2026-05-29",
          "pick_id": "20260529-NHL-MTL-CAR-SPREAD",
          "pick": "Carolina Hurricanes -1.5",
          "game": "MTL @ CAR",
          "status": "WIN",
          "after_streak": 4
        },
        {
          "date": "2026-05-28",
          "pick_id": "20260528-NBA-OKC-SA-SPREAD",
          "pick": "San Antonio Spurs -3.5",
          "game": "OKC @ SA",
          "status": "WIN",
          "after_streak": 3
        },
        {
          "date": "2026-05-27",
          "pick_id": "20260527-MLB-LAA-DET-TOTAL",
          "pick": "Under 9.0",
          "game": "LAA @ DET",
          "status": "WIN",
          "after_streak": 2
        },
        {
          "date": "2026-05-26",
          "pick_id": "20260526-MLB-STL-MIL-RUNLINE",
          "pick": "Milwaukee Brewers -1.5",
          "game": "STL @ MIL",
          "status": "WIN",
          "after_streak": 1
        },
        {
          "date": "2026-05-25",
          "pick_id": "20260525-MLB-CHC-PIT-ML",
          "pick": "Chicago Cubs ML",
          "game": "CHC @ PIT",
          "status": "LOSS",
          "after_streak": 0
        },
        {
          "date": "2026-05-24",
          "pick_id": "20260524-MLB-CLE-PHI-ML",
          "pick": "Cleveland Guardians ML",
          "game": "CLE @ PHI",
          "status": "LOSS",
          "after_streak": 0
        },
        {
          "date": "2026-05-23",
          "pick_id": "20260523-MLB-CLE-PHI-TOTAL",
          "pick": "Under 7.0",
          "game": "CLE @ PHI",
          "status": "WIN",
          "after_streak": 3
        },
        {
          "date": "2026-05-22",
          "pick_id": "20260522-MLB-HOU-CHC-TOTAL",
          "pick": "Under 8.0",
          "game": "HOU @ CHC",
          "status": "WIN",
          "after_streak": 2
        },
        {
          "date": "2026-05-21",
          "pick_id": "20260521-MLB-COL-ARI-TOTAL",
          "pick": "Under 9.5",
          "game": "COL @ ARI",
          "status": "WIN",
          "after_streak": 1
        },
        {
          "date": "2026-05-20",
          "pick_id": "20260520-MLB-ATL-MIA-TOTAL",
          "pick": "Under 7.0",
          "game": "ATL @ MIA",
          "status": "LOSS",
          "after_streak": 0
        },
        {
          "date": "2026-05-19",
          "pick_id": "20260519-MLB-NYM-WSH-ML",
          "pick": "New York Mets ML",
          "game": "NYM @ WSH",
          "status": "LOSS",
          "after_streak": 0
        },
        {
          "date": "2026-05-18",
          "pick_id": "20260518-MLB-BAL-TB-TOTAL",
          "pick": "Under 7.5",
          "game": "BAL @ TB",
          "status": "LOSS",
          "after_streak": 0
        },
        {
          "date": "2026-05-17",
          "pick_id": "20260517-MLB-NYY-NYM-ML",
          "pick": "New York Mets ML",
          "game": "NYY @ NYM",
          "status": "WIN",
          "after_streak": 2
        },
        {
          "date": "2026-05-16",
          "pick_id": "20260516-MLB-PHI-PIT-TOTAL",
          "pick": "Under 8.5",
          "game": "PHI @ PIT",
          "status": "WIN",
          "after_streak": 1
        }
      ],
      "updated_at": "2026-05-30T20:06:52.934739-04:00"
    },
    "all_time_record": {
      "record": "8-5-0",
      "wins": 8,
      "losses": 5,
      "pushes": 0,
      "pending": 1,
      "total_picks": 14,
      "settled_picks": 13,
      "units_pl": 4.161,
      "roi_pct": 21.34,
      "win_rate_pct": 61.54,
      "avg_clv_cents": 0.0,
      "longest_w_streak": 4,
      "longest_l_streak": 3,
      "biggest_win_units": 2.2,
      "biggest_loss_units": -1.5
    }
  },
  "bonus_track": {
    "label": "For the Juice \u2014 longshot bonus picks, not part of the official record",
    "all_time": {
      "record": "0-0-0",
      "wins": 0,
      "losses": 0,
      "pushes": 0,
      "pending": 1,
      "total_picks": 1,
      "settled_picks": 0,
      "units_pl": 0,
      "roi_pct": 0.0,
      "win_rate_pct": 0.0,
      "avg_clv_cents": 0.0,
      "longest_w_streak": 0,
      "longest_l_streak": 0,
      "biggest_win_units": 0,
      "biggest_loss_units": 0
    },
    "total": 1
  },
  "totals": {
    "all_picks": 51,
    "bonus_picks": 1,
    "sports": [
      "MLB",
      "NBA",
      "NHL"
    ]
  }
}